Metadata-Version: 2.1
Name: digimat.bac0
Version: 0.0.23
Summary: Digimat BACnet BAC0 Wrapper
Home-page: http://www.digimat.ch
Author: Frederic Hess
Author-email: fhess@st-sa.ch
License: PSF
Classifier: Development Status :: 4 - Beta
Classifier: Programming Language :: Python :: 3
